deephaven_core/proto/application_pb2.py
deephaven_core/proto/application_pb2_grpc.py
deephaven_core/proto/config_pb2.py
deephaven_core/proto/config_pb2_grpc.py
deephaven_core/proto/console_pb2.py
deephaven_core/proto/console_pb2_grpc.py
deephaven_core/proto/hierarchicaltable_pb2.py
deephaven_core/proto/hierarchicaltable_pb2_grpc.py
deephaven_core/proto/inputtable_pb2.py
deephaven_core/proto/inputtable_pb2_grpc.py
deephaven_core/proto/object_pb2.py
deephaven_core/proto/object_pb2_grpc.py
deephaven_core/proto/partitionedtable_pb2.py
deephaven_core/proto/partitionedtable_pb2_grpc.py
deephaven_core/proto/session_pb2.py
deephaven_core/proto/session_pb2_grpc.py
deephaven_core/proto/storage_pb2.py
deephaven_core/proto/storage_pb2_grpc.py
deephaven_core/proto/table_pb2.py
deephaven_core/proto/table_pb2_grpc.py
deephaven_core/proto/ticket_pb2.py
deephaven_core/proto/ticket_pb2_grpc.py
pydeephaven/__init__.py
pydeephaven/_app_service.py
pydeephaven/_arrow.py
pydeephaven/_arrow_flight_service.py
pydeephaven/_batch_assembler.py
pydeephaven/_config_service.py
pydeephaven/_console_service.py
pydeephaven/_input_table_service.py
pydeephaven/_plugin_obj_service.py
pydeephaven/_session_service.py
pydeephaven/_table_interface.py
pydeephaven/_table_ops.py
pydeephaven/_table_service.py
pydeephaven/_utils.py
pydeephaven/agg.py
pydeephaven/dherror.py
pydeephaven/filters.py
pydeephaven/py.typed
pydeephaven/query.py
pydeephaven/session.py
pydeephaven/table.py
pydeephaven/ticket.py
pydeephaven/updateby.py
pydeephaven/utils.py
pydeephaven/experimental/__init__.py
pydeephaven/experimental/plugin_client.py
pydeephaven-41.1.dist-info/METADATA
pydeephaven-41.1.dist-info/WHEEL
pydeephaven-41.1.dist-info/top_level.txt
pydeephaven-41.1.dist-info/RECORD
