Metadata-Version: 2.1
Name: pydeephaven
Version: 41.1
Summary: The Deephaven Python Client
Home-page: https://deephaven.io/
Author: Deephaven Data Labs
Author-email: python@deephaven.io
License: Deephaven Community License Agreement Version 1.0
Classifier: Development Status :: 4 - Beta
Classifier: Intended Audience :: Developers
Classifier: License :: Other/Proprietary License
Classifier: Programming Language :: Python
Classifier: Programming Language :: Python :: 3
Classifier: Programming Language :: Python :: 3 :: Only
Classifier: Programming Language :: Python :: 3.9
Classifier: Programming Language :: Python :: 3.10
Classifier: Programming Language :: Python :: 3.11
Classifier: Programming Language :: Python :: 3.12
Classifier: Programming Language :: Python :: 3.13
Requires-Python: >=3.9
Requires-Dist: pyarrow
Requires-Dist: bitstring
Requires-Dist: grpcio
Requires-Dist: protobuf
Requires-Dist: numpy
Requires-Dist: pandas
